psy_view/__init__.py
psy_view/__main__.py
psy_view/_version.py
psy_view/dialogs.py
psy_view/ds_widget.py
psy_view/plotmethods.py
psy_view/py.typed
psy_view/rcsetup.py
psy_view/utils.py
psy_view/icons/color_settings.png
psy_view/icons/color_settings.png.license
psy_view/icons/proj_settings.png
psy_view/icons/proj_settings.png.license
psy_view-0.3.0.dist-info/CC-BY-4.0.txt
psy_view-0.3.0.dist-info/CC0-1.0.txt
psy_view-0.3.0.dist-info/LGPL-3.0-only.txt
psy_view-0.3.0.dist-info/METADATA
psy_view-0.3.0.dist-info/WHEEL
psy_view-0.3.0.dist-info/entry_points.txt
psy_view-0.3.0.dist-info/top_level.txt
psy_view-0.3.0.dist-info/RECORD
